nqm/iotdatabase/__init__.py
nqm/iotdatabase/_datasetdata.py
nqm/iotdatabase/_sqlitealchemyconverter.py
nqm/iotdatabase/_sqliteconstants.py
nqm/iotdatabase/_sqliteinfotable.py
nqm/iotdatabase/_sqliteschemaconverter.py
nqm/iotdatabase/_sqliteutils.py
nqm/iotdatabase/database.py
nqm/iotdatabase/ndarray/__init__.py
nqm/iotdatabase/ndarray/fileio.py
nqm/iotdatabase/ndarray/ndarray.py
nqm/iotdatabase/ndarray/storageformats.py
nqm.iotdatabase-1.1.5.dist-info/WHEEL
nqm.iotdatabase-1.1.5.dist-info/METADATA
nqm.iotdatabase-1.1.5.dist-info/RECORD
