Metadata-Version: 2.1
Name: nqm.iotdatabase
Version: 1.1.5
Summary: Library for accessing a local nqm-iot-database
Home-page: https://github.com/nqminds/nqm-iot-database-py
Author: Alois Klink
Author-email: alois.klink@gmail.com
Requires-Python: >=3.6,<4.0
Classifier: Programming Language :: Python :: 3
Classifier: Programming Language :: Python :: 3.6
Classifier: Programming Language :: Python :: 3.7
Requires-Dist: future (>=0.18.2,<0.19.0)
Requires-Dist: mongosql (>=2.0.8,<3.0.0)
Requires-Dist: numpy (>=1.17.4,<2.0.0)
Requires-Dist: shortuuid (>=0.5.0,<0.6.0)
Requires-Dist: sqlalchemy (>=1.3.11,<2.0.0)
Project-URL: Repository, https://github.com/nqminds/nqm-iot-database-py
